LICENSE
MANIFEST.in
README.md
pyproject.toml
setup.cfg
setup.py
baseapp_drf_view_action_permissions/__init__.py
baseapp_drf_view_action_permissions/action.py
baseapp_drf_view_action_permissions/admin.py
baseapp_drf_view_action_permissions/apps.py
baseapp_drf_view_action_permissions/middleware.py
baseapp_drf_view_action_permissions/mixin.py
baseapp_drf_view_action_permissions/models.py
baseapp_drf_view_action_permissions/settings.py
baseapp_drf_view_action_permissions/utils.py
baseapp_drf_view_action_permissions.egg-info/PKG-INFO
baseapp_drf_view_action_permissions.egg-info/SOURCES.txt
baseapp_drf_view_action_permissions.egg-info/dependency_links.txt
baseapp_drf_view_action_permissions.egg-info/requires.txt
baseapp_drf_view_action_permissions.egg-info/top_level.txt
baseapp_drf_view_action_permissions/migrations/0001_initial.py
baseapp_drf_view_action_permissions/migrations/0002_iprestriction.py
baseapp_drf_view_action_permissions/migrations/__init__.py
baseapp_drf_view_action_permissions/tests/__init__.py
baseapp_drf_view_action_permissions/tests/conftest.py
baseapp_drf_view_action_permissions/tests/factories.py
baseapp_drf_view_action_permissions/tests/test_integration.py
baseapp_drf_view_action_permissions/tests/test_migration_health_check.py
baseapp_drf_view_action_permissions/tests/test_unit.py